pylana/__init__.py
pylana/api.py
pylana/dashboards.py
pylana/decorators.py
pylana/filter.py
pylana/logs.py
pylana/resources.py
pylana/shiny_dashboards.py
pylana/structures.py
pylana/users.py
pylana/utils.py
pylana/v1.py
pylana/v2.py
pylana/aggregation/__init__.py
pylana/aggregation/core.py
pylana/aggregation/groupings.py
pylana/aggregation/metrics.py
pylana/aggregation/utils.py
pylana-0.2.1.dist-info/LICENSE
pylana-0.2.1.dist-info/METADATA
pylana-0.2.1.dist-info/WHEEL
pylana-0.2.1.dist-info/top_level.txt
pylana-0.2.1.dist-info/RECORD
