Metadata-Version: 2.1
Name: pylana
Version: 0.2.1
Summary: Python API for LANA Process Mining
Home-page: https://github.com/lanalabs/pylana
Author: Lana Labs GmbH
Author-email: support@lanalabs.com
License: Apache2
Platform: UNKNOWN
Classifier: Development Status :: 4 - Beta
Classifier: Intended Audience :: System Administrators
Classifier: License :: OSI Approved :: Apache Software License
Classifier: Programming Language :: Python :: 3
Requires-Dist: requests
Requires-Dist: pandas
